LICENSE
README.md
setup.py
xscreenfilter/__init__.py
xscreenfilter/__main__.py
xscreenfilter/list_monitors.py
xscreenfilter/main.py
xscreenfilter/xscreenfilter.py
xscreenfilter.egg-info/PKG-INFO
xscreenfilter.egg-info/SOURCES.txt
xscreenfilter.egg-info/dependency_links.txt
xscreenfilter.egg-info/requires.txt
xscreenfilter.egg-info/top_level.txt